pluau-0.1.2.dist-info/METADATA
pluau-0.1.2.dist-info/WHEEL
pluau.libs/libgcc_s-e52197c3.so.1
pluau.libs/libstdc++-405035b3.so.6
pluau/__init__.py
pluau/_pluau.cpython-39-aarch64-linux-gnu.so
pluau/_pluau.pyi
pluau/args.py
pluau/utils.py
pluau-0.1.2.dist-info/RECORD
