Metadata-Version: 2.4
Name: pluau
Version: 0.1.2
Classifier: Programming Language :: Rust
Classifier: Programming Language :: Python :: Implementation :: CPython
Classifier: Programming Language :: Python :: Implementation :: PyPy
Summary: Pluau: Python bindings for the Lua(u) programming language
Keywords: lua,luau,scripting,bindings,ffi,lupa
License-Expression: MIT
Requires-Python: >=3.8
Project-URL: Repository, https://github.com/gluau/pluau.git
Project-URL: Issues, https://github.com/gluau/pluau/issues
